LICENSE
README.md
setup.cfg
setup.py
src/dcli/__init__.py
src/dcli/dcli.py
src/decorator_cli.egg-info/PKG-INFO
src/decorator_cli.egg-info/SOURCES.txt
src/decorator_cli.egg-info/dependency_links.txt
src/decorator_cli.egg-info/top_level.txt