Metadata-Version: 2.1
Name: decorator-cli
Version: 0.1.6
Summary: functional-oriented cli decorator.
Home-page: https://github.com/vNaonLu/dcli
Author: Naon Lu
Author-email: vnaonlu0101453@gmail.com
License: MIT
Keywords: decorator cli
Platform: UNKNOWN
Classifier: Development Status :: 3 - Alpha
Classifier: Intended Audience :: Developers
Classifier: Topic :: Software Development :: Build Tools
Classifier: License :: OSI Approved :: MIT License
Classifier: Programming Language :: Python :: 3.9
Classifier: Programming Language :: Python :: 3.10
Requires-Python: >=3.9
License-File: LICENSE
